dtcli/__init__.py
dtcli/__main__.py
dtcli/api.py
dtcli/building.py
dtcli/click_helpers.py
dtcli/constants.py
dtcli/delete_extension.py
dtcli/dev.py
dtcli/scripts/__init__.py
dtcli/scripts/dt.py
dtcli/scripts/utility.py
dtcli/server_api.py
dtcli/shim.py
dtcli/signing.py
dtcli/utils.py
dtcli/validate_schema.py
dtcli/version.py
dt_cli-1.6.21.dist-info/LICENSE
dt_cli-1.6.21.dist-info/METADATA
dt_cli-1.6.21.dist-info/WHEEL
dt_cli-1.6.21.dist-info/entry_points.txt
dt_cli-1.6.21.dist-info/RECORD
