Metadata-Version: 2.1
Name: dt-cli
Version: 1.6.21
Summary: Dynatrace CLI
Home-page: https://github.com/dynatrace-oss/dt-cli
License: Apache-2.0
Keywords: dynatrace,cli,extensions
Author: Vagiz Duseev
Author-email: vagiz.duseev@dynatrace.com
Maintainer: Vagiz Duseev
Maintainer-email: vagiz.duseev@dynatrace.com
Requires-Python: >=3.8,<4.0
Classifier: License :: OSI Approved :: Apache Software License
Classifier: Programming Language :: Python :: 3
Classifier: Programming Language :: Python :: 3.8
Classifier: Programming Language :: Python :: 3.9
Classifier: Programming Language :: Python :: 3.10
Classifier: Programming Language :: Python :: 3.11
Classifier: Programming Language :: Python :: 3.12
Requires-Dist: PyYAML (>=6.0,<7.0)
Requires-Dist: asn1crypto (>=1.4,<2.0)
Requires-Dist: click-aliases (>=1.0,<2.0)
Requires-Dist: cryptography (>3)
Requires-Dist: jsonschema (>=4.7,<5.0)
Requires-Dist: requests (>=2.26,<3.0)
Requires-Dist: typer (>=0,<1)
Requires-Dist: wheel (>=0,<1)
Project-URL: Documentation, https://github.com/dynatrace-oss/dt-cli
Project-URL: Repository, https://github.com/dynatrace-oss/dt-cli
